[
    {
        "id": "1",
        "title": "Single cause, single effect",
        "text": "When the red button is pushed the system shuts down.",
        "classification": {
            "causal": true,
            "confidence": 0.9
        },
        "labels": [
            {"id": "T1", "name": "Keyword", "begin": 0, "end": 4},
    
            {"id": "T2", "name": "Cause1", "begin": 5, "end": 29},
            {"id": "T3", "name": "Variable", "begin": 5, "end": 19},
            {"id": "T4", "name": "Condition", "begin": 20, "end": 29},
            
            {"id": "T5", "name": "Effect1", "begin": 30, "end": 51},
            {"id": "T6", "name": "Variable", "begin": 30, "end": 40},
            {"id": "T7", "name": "Condition", "begin": 41, "end": 51}
        ],
        "graph": {
            "desc": "In this very explicit case with only one cause and one effect, the CEG consists of exactly two nodes connected by a normal edge.",
            "nodes": [
                {"id": 1, "variable": "the red button", "condition": "is pushed"},
                {"id": 2, "variable": "the system", "condition": "shuts down"}
            ],
            "edges": [
                {"source": 1, "target": 2, "negate": false}
            ]
        },
        "testsuite": {
            "desc": "Two test cases are generated based on the cause-effect graph: the positive, explicit case that happens, when the cause is true, and the negative, implicit case, that happens when the effect ist false.",
            "inputparams": [
                {"id": 1, "text": "the red button"}
            ],
            "outputparams": [
                {"id": 2, "text": "the system"}
            ],
            "testcases": [
                {
                    "id": 1, 
                    "configurations": [{"inputid": 1, "text": "is pushed"}],
                    "outcome": [{"outputid": 2, "text": "shuts down"}]
                }, {
                    "id": 2, 
                    "configurations": [{"inputid": 1, "text": "not is pushed"}],
                    "outcome": [{"outputid": 2, "text": "not shuts down"}]
                }
            ]
        }
    }, 
    {
        "id": "2",
        "title": "Two conjunctive causes, single effect",
        "text": "When the red button is pushed and the power fails the system shuts down.",
        "classification": {
            "causal": true,
            "confidence": 0.9
        },
        "labels": [
            {"id": "T1", "name": "Keyword", "begin": 0, "end": 4},
    
            {"id": "T2", "name": "Cause1", "begin": 5, "end": 29},
            {"id": "T3", "name": "Variable", "begin": 5, "end": 19},
            {"id": "T4", "name": "Condition", "begin": 20, "end": 29},
    
            {"id": "T5", "name": "Conjunction", "begin": 30, "end": 33},
    
            {"id": "T6", "name": "Cause2", "begin": 34, "end": 49},
            {"id": "T7", "name": "Variable", "begin": 34, "end": 43},
            {"id": "T8", "name": "Condition", "begin": 44, "end": 49},
    
            {"id": "T9", "name": "Effect1", "begin": 50, "end": 71},
            {"id": "T10", "name": "Variable", "begin": 50, "end": 60},
            {"id": "T12", "name": "Condition", "begin": 61, "end": 71}
        ],
        "graph": {
            "desc": "If two causes and a conjunction between them is detected, then the two cause nodes are connected with an intermediate node representing the conjunction. The conjunction represents that both events must be true in order for the effect to occur.",
            "nodes": [
                {"id": 1, "variable": "the red button", "condition": "is pushed"},
                {"id": 2, "variable": "the power", "condition": "fails"},
                {"id": 3, "variable": "", "condition": "", "type": "AND"},
                {"id": 4, "variable": "the system", "condition": "shuts down"}
            ],
            "edges": [
                {"source": 1, "target": 3, "negate": false},
                {"source": 2, "target": 3, "negate": false},
                {"source": 3, "target": 4, "negate": false}
            ]
        },
        "testsuite": {
            "desc": "For this acceptance test, next to the trivial positive test case two negative test cases are created, one for each cause to be responsible for the conjunction to be evaluated to false. It is unnecessary to also test the fourth possible case, where both causes are evaluated to false, as the existing two negative test cases already verify that each cause can be responsible for evaluating the conjunction to false.",
            "inputparams": [
                {"id": 1, "text": "the red button"},
                {"id": 2, "text": "the power"}
            ],
            "outputparams": [
                {"id": 3, "text": "the system"}
            ],
            "testcases": [
                {
                    "id": 1, 
                    "configurations": [{"inputid": 1, "text": "is pushed"}, {"inputid": 2, "text": "fails"}],
                    "outcome": [{"outputid": 3, "text": "shuts down"}]
                }, {
                    "id": 2, 
                    "configurations": [{"inputid": 1, "text": "is pushed"}, {"inputid": 2, "text": "not fails"}],
                    "outcome": [{"outputid": 3, "text": "not shuts down"}]
                }, {
                    "id": 3, 
                    "configurations": [{"inputid": 1, "text": "not is pushed"}, {"inputid": 2, "text": "fails"}],
                    "outcome": [{"outputid": 3, "text": "not shuts down"}]
                }
            ]
        }
    }
]